MANIFEST.in
setup.cfg
setup.py
django_inventory_exnodes.egg-info/PKG-INFO
django_inventory_exnodes.egg-info/SOURCES.txt
django_inventory_exnodes.egg-info/dependency_links.txt
django_inventory_exnodes.egg-info/top_level.txt
product/__init__.py
product/admin.py
product/apps.py
product/models.py
product/serializers.py
product/tests.py
product/urls.py
product/views.py
product/migrations/0001_initial.py
product/migrations/__init__.py